ffas/__init__.py
ffas/__main__.py
ffas/basic.py
ffas/config.py
ffas/db.py
ffas/encoding.py
ffas/files/__init__.py
ffas/files/mime.types
ffas/find_pairs.py
ffas/generate.py
ffas/misc.py
ffas/sample.py
ffas/show_pairs.py
ffas/terminal.py
ffas/videostore.py
ffmpeg_auto_settings-2.1.1.dist-info/COPYING
ffmpeg_auto_settings-2.1.1.dist-info/METADATA
ffmpeg_auto_settings-2.1.1.dist-info/WHEEL
ffmpeg_auto_settings-2.1.1.dist-info/entry_points.txt
ffmpeg_auto_settings-2.1.1.dist-info/RECORD
