Metadata-Version: 2.1
Name: ffmpeg-auto-settings
Version: 2.1.1
Summary: 
Home-page: https://gitlab.com/liancea/ffmpeg-auto-settings
License: GPL-3.0-only
Author: liancea
Author-email: liancea@mehrkoffe.in
Requires-Python: >=3.10,<4.0
Classifier: License :: OSI Approved :: GNU General Public License v3 (GPLv3)
Classifier: Programming Language :: Python :: 3
Classifier: Programming Language :: Python :: 3.10
Classifier: Programming Language :: Python :: 3.11
Classifier: Programming Language :: Python :: 3.12
Requires-Dist: blessings (>=1.7,<2.0)
Requires-Dist: humanize (>=4.8.0,<5.0.0)
Requires-Dist: inquirerpy (>=0.3.4,<0.4.0)
Requires-Dist: prettytable (>=3.9.0,<4.0.0)
Requires-Dist: python-magic (>=0.4.27,<0.5.0)
Requires-Dist: python-magic-bin (>=0.4.14,<0.5.0) ; sys_platform == "win32"
Requires-Dist: sqlalchemy (>=2.0,<2.1)
Requires-Dist: tomlkit (>=0.12.3,<0.13.0)
Project-URL: Documentation, https://liancea.gitlab.io/ffmpeg-auto-settings/
Project-URL: Repository, https://gitlab.com/liancea/ffmpeg-auto-settings
